MANIFEST.in
README.txt
setup.py
lfs_moip/__init__.py
lfs_moip/listeners.py
lfs_moip/models.py
lfs_moip/tests.py
lfs_moip/views.py
lfs_moip.egg-info/PKG-INFO
lfs_moip.egg-info/SOURCES.txt
lfs_moip.egg-info/dependency_links.txt
lfs_moip.egg-info/not-zip-safe
lfs_moip.egg-info/requires.txt
lfs_moip.egg-info/top_level.txt