Metadata-Version: 1.1
Name: lfs-moip
Version: 1.0b2
Summary: Integration of MoIP into LFS
Home-page: https://github.com/alanjds/lfs-moip
Author: Alan Justino da Silva
Author-email: alan.justino@yahoo.com.br
License: BSD
Download-URL: https://github.com/alanjds/lfs-moip/tarball/1.0b2
Keywords: django e-commerce online-shop moip
Platform: UNKNOWN
Classifier: Environment :: Web Environment
Classifier: Framework :: Django
Classifier: License :: OSI Approved :: BSD License
Classifier: Operating System :: OS Independent
Classifier: Programming Language :: Python
